turbospectrum/__init__.py
turbospectrum/atmos.py
turbospectrum/atomic.py
turbospectrum/synthesis.py
turbospectrum/utils.py
turbospectrum/data/Anstee-1802-2014.dat
turbospectrum/data/CIA.H-He.dat
turbospectrum/data/CIA.H2-H.dat
turbospectrum/data/CIA.H2-H2.Yi.dat
turbospectrum/data/CIA.H2-He.dat
turbospectrum/data/E161
turbospectrum/data/Hlinedata
turbospectrum/data/IRWIN_atoms_v07.3.dat
turbospectrum/data/IRWIN_molecules_v15.1.dat
turbospectrum/data/LISTE_molecules_all_v19.1.dat
turbospectrum/data/NHcont_Stancil_2019.dat
turbospectrum/data/SPECIES_LTE_NLTE.dat
turbospectrum/data/atomicweights.dat
turbospectrum/data/bpo_self.grid.DEC
turbospectrum/data/bpo_self.grid.SUN
turbospectrum/data/chcont.dat
turbospectrum/data/energy-levels-BarberH2O.txt
turbospectrum/data/h2olevels.morbid
turbospectrum/data/h2omolk.dat
turbospectrum/data/jonabs_vac_v19.2.dat
turbospectrum/data/ohcont.dat
turbospectrum/data/stehle.dat.DEC
turbospectrum/data/stehle.dat.SUN
turbospectrum/data/tableU2.dat
turbospectrum/data/tableU3.dat
turbospectrum/data/vcsbalmer.dat
turbospectrum/test/nlte_linelist_test.txt
turbospectrum/test/s6000_g+1.0_m0.5.mod
turbospectrum/test/test-babsma
turbospectrum/test/test-bsyn
turbospectrum-1.0.1.dist-info/LICENSE
turbospectrum-1.0.1.dist-info/METADATA
turbospectrum-1.0.1.dist-info/WHEEL
turbospectrum-1.0.1.dist-info/top_level.txt
turbospectrum-1.0.1.dist-info/RECORD
